gittable/__init__.py
gittable/__main__.py
gittable/_utilities.py
gittable/download.py
gittable/py.typed
gittable/tag_version.py
gittable-0.2.0.dist-info/METADATA
gittable-0.2.0.dist-info/WHEEL
gittable-0.2.0.dist-info/entry_points.txt
gittable-0.2.0.dist-info/RECORD
