Metadata-Version: 2.4
Name: gittable
Version: 0.2.0
Summary: Get stuff from Git
Project-URL: Documentation, https://gittable.enorganic.org
Project-URL: Repository, https://github.com/enorganic/gittable
Author-email: david@belais.me
License-Expression: MIT
Keywords: git
Requires-Python: ~=3.9
